images_utils
