Metadata-Version: 1.1
Name: images-utils
Version: 0.0.8
Summary: images-utils has recognition function
Home-page: https://github.com/suckmybigdick/flask-wechat-utils
Author: UNKNOWN
Author-email: 13250270761@163.com
License: UNKNOWN
Platform: UNKNOWN
Classifier: Programming Language :: Python :: 2
Classifier: License :: OSI Approved :: MIT License
Classifier: Operating System :: OS Independent
